{"doc_id": "1977-03-15-fomc-minutes", "date": "1977-03-15", "chair": "Arthur Burns", "combined_score": 0.0, "combined_label": "neutral", "lexicon_score": 0.0, "word_count": 1495, "text": "                                                                                             Committee\n                    Meeting  of  Federal  Open  Market\n                                                   March  15,   1977\n                                          MINUTES  OF  ACTIONS\n                        A  meeting  of   the  Federal  Open  Committee  was  held\n in  the  offices   of  the  Board  of  Governors  of   the  Federal\nReserve  System  in  Washington,  D.  C.,    on  Tuesday,  March  15,\n 1977,   beginning  at   9:30  a.m.\n            PRESENT:     Mr.   Burns,   Chairman\n                                    Mr.  Volcker,  Vice  Chairman\n                                    Mr.  Coldwell\n                                    Mr.   Gardner\n                                    Mr.   Guffey\n                                    Mr.   Jackson\n                                    Mr.   Lilly\n                                    Mr.  Mayo\n                                    Mr.  Morris\n                                    Mr.  Partee\n                                    Mr.  Roos\n                                    Mr.  Wallich\n                                    Messrs.  Balles,  Baughman,  Eastburn,  and  Winn,\n                                                Alternate  Members  of   the  Federal  Open\n                                                Market   Committee\n                                    Messrs.  Black  and  Kimbrel,  Presidents   of  the\n                                                Federal  Reserve  Banks  of  Richmond  and\n                                                Altanta,  respectively\n                                                Mr.   Broida,   Secretary\n                                                Mr.   Altmann,  Deputy   Secretary\n                                                Mr.   Bernard,  Assistant   Secretary\n                                                Mr.  O'Connell,   General  Counsel\n                                                Mr.   Axilrod,  Economist\n                                                Messrs.  Balbach,  T.   Davis,   Ettin,\n                                                           Kichline,  Reynolds,  Scheld,\n                                                           Truman,   and  Zeisel,  Associate\n                                                           Economists\n3/15/77                                                             -   2   -\n                                                 Mr.  Holmes,  Manager   System  Open  Market\n                                                             Account\n                                                 Mr.   Pardee,  Deputy  Manager   for  Foreign\n                                                             Operations\n                                                 Mr.  Sternlight,  Deputy  Manager   for\n                                                             Domestic  Operations\n                                                 Mr.   Hudson,  Assistant   to  the  Chairman,\n                                                             Board  of  Governors\n                                                 Messrs.  Coyne  and   Keir,  Assistants  to\n                                                             the  Board  of   Governors\n                                                 Mrs.   Farar,  Economist,   Open  Market\n                                                             Secretariat,   Board  of   Governors\n                                                 Mrs.  Deck,  Staff  Assistant,   Open  Market\n                                                             Secretariat,  Board  of  Governors\n                                                 Mr.   Van  Nice,  First   Vice  President,\n                                                             Federal  Reserve  Bank  of  Minneapolis\n                                                Messrs.  Boehne,  Davis,  and  Parthemos,\n                                                            Senior  Vice  Presidents,  Federal\n                                                            Reserve  Banks  of  Philadelphia,\n                                                            Cleveland,  and  Richmond,\n                                                            respectively\n                                                Messrs.  Brandt,   Burns,  Fieleke,  Fousek,\n                                                            and  Keran,  Vice  Presidents,  Federal\n                                                            Reserve  Banks  of  Atlanta,  Dallas,\n                                                            Boston,  New  York,  and  San  Francisco\n                                                            respectively\n                                                Mr.  Kareken,  Economic  Adviser,  Federal\n                                                            Reserve  Bank  of  Minneapolis\n                                                Mr.  Meek,  Monetary  Adviser,  Federal\n                                                            Reserve   Bank  of  New  York\n                         In  the   agenda  for   this  meeting,   it   was  reported\nthat   advices  of   the   election  of   the  following  members  and\nalternate  members  of  the  Federal  Open  Market   Committee  for\n 3/15/77                                                            -   3  -\n the  year  commencing  March   1,  1977,  had  been   received  by  the\n Secretary  and  the  named   individuals  had  executed  their\n oaths  of   office.\n                         The  elected  members  and  alternate  members  were\n as   follows:\n Frank  E.   Morris,  President   of  the  Federal  Reserve  Bank  of\n             Boston,  with  David  P.   Eastburn,  President   of  the\n             Federal  Reserve  Bank  of   Philadelphia,  as   alternate;\n Paul  A.  Volcker,  President   of   the  Federal   Reserve  Bank  of\n             New  York,  with  Thomas  M.   Timlen,  First   Vice  President\n             of   the  Federal   Reserve  Bank  of  New  York,  as   alternate;\n Robert  P.   Mayo,  President  of   the  Federal  Reserve  Bank  of\n             Chicago,  with  Willis  J.   Winn,  President   of  the  Federal\n             Reserve  Bank  of   Cleveland,  as  alternate;\n Lawrence  K.  Roos,  President   of  the   Federal  Reserve   Bank  of\n             St.   Louis,  with  Ernest  T.  Baughman,  President   of   the\n             Federal  Reserve  Bank  of  Dallas,  as   alternate;\n James  R.  Guffey,  President   of   the   Federal  Reserve   Bank  of\n             Kansas  City,  with  John  J.  Balles,  President   of   the\n             the  Federal  Reserve  Bank  of   San  Francisco,   as   alternate.\n                        By   unanimous  vote,  the   following  officers  of   the\nFederal   Open  Market   Committee  were  elected  to  serve   until\n the   election  of  their   successors   at  the  first   meeting  of\n the  Committee  after   February  28,   1978,  with   the  understanding\nthat   in  the   event  of   the  discontinuance   of  their  official\n connection  with  the   Board  of   Governors  or  with   a  Federal\nReserve  Bank,  as  the   case  might  be,   they  would   cease   to\n have  any  official   connnection  with  the  Federal   Open  Market\nCommittee:\n3/15/77                                                            -   4   -\n Arthur  F.   Burns                                                         Chairman\n Paul  A.  Volcker                                                          Vice  Chairman\n Arthur  L.   Broida                                                        Secretary\n Murray  Altmann                                                            Deputy  Secretary\n Normand  R.  V.  Bernard                                                   Assistant   Secretary\n Thomas  J.  O'Connell                                                      General  Counsel\n Edward  G.   Guy                                                           Deputy  General   Counsel\n Baldwin  B.  Tuttle                                                        Assistant  General   Counsel\n Stephen  H.  Axilrod                                                       Economist\n Anatol   Balbach,  Richard  G.\n     Davis,  Thomas  Davis,  Robert\n     Eisenmenger,  Edward  Ettin,\n      James  L.  Kichline,  Karl\n      Scheld,  John  E.  Reynolds,\n     Edward  M.  Truman,   Joseph\n     S.   Zeisel                                                            Associate  Economists\n                        By  unanimous  vote,   the  Federal  Reserve  Bank  of\nNew  York  was   selected  to  execute  transactions  for  the\n System  Open  Market  Account   until  the  adjournment  of   the\n first  meeting  of  the  Federal   Open  Market   Committee  after\n February  28,   1978.\n                        By  unanimous  vote,   Alan  R.   Holmes,  Peter  D.\n Sternlight,   and  Scott  E.   Pardee  were   selected  to   serve  at\n the  pleasure   of  the  Committee   in  the  capacities  of  Manager\n of  the  System  Open  Market  Account,   Deputy   Manager  for\nDomestic  Operations,   and  Deputy  Manager   for  Foreign  Oper\n ations,   respectively,  on  the  understanding  that   their\n selection  was  subject  to  their  being   satisfactory  to  the\n Federal  Reserve  Bank  of  New  York.\n3/15/77                                                       -   5   -\n                         Secretary's  note:     Advice  was   subsequently\n                         received  that   the   selections  indicated  above\n                        were  satisfactory  to   the  Federal  Reserve\n                        Bank  of  New  York.\n                        By  unanimous  vote,  the  minutes  of   actions  taken\n at   the  meeting  of  the  Federal  Open  Market  Committee  held\n on  February   15,  1977,  were  approved.\n                        By  unanimous  vote,   System  open   market  transactions\n in   foreign  currencies  during  the  period  February  15   through\nMarch   14,   1977,  were  approved,   ratified,  and   confirmed.\n                        By  unanimous  vote,   System  open  market   transactions\n in  Government  securities,   agency  obligations,   and  bankers'\n acceptances  during  the  period  February   15   through  March   14,\n 1977,  were  approved,  ratified,   and  confirmed.\n                        By  unanimous   vote,   the  Federal  Reserve  Bank  of\nNew  York  was  authorized  and   directed,  until  otherwise\n directed  by   the  Committee,  to   execute  transactions  in  the\n System  Account   in   accordance  with  the  following  domestic\npolicy  directive:\n                                    The   information  reviewed  at   this  meeting\n                        suggests  that   growth   in   real   output   of  goods\n                        and  services  has  increased  in   the   current\n                        quarter   from  the  reduced  pace   in  the   fourth\n                        quarter   of   1976.     In  February   industrial\n                        output   and   retail  sales   expanded  substantially\n                        after  being  held  down   for   a  time  by  the  effects\n                        of  unusually   severe  weather.     Employment  rose\n                        considerably  further;   the  unemployment   rate\n3/15/77                                                           -   6  -\n                        increased  somewhat   to  7.5  per  cent--as   the\n                        labor  force  more  than  recovered   the  decline\n                        of   January--but   it   remained  below   the  7.8\n                        per  cent   of  December.     The  wholesale  price\n                        index  for  all  commodities  rose  substantially\n                        in  February,  reflecting   large  increases\n                        for   farm  products   and  foods   and  for   fuels\n                        and  power.     The   index  of  average  wage  rates\n                        rose  more  moderately   over  the  first  2  months\n                        of   1977  than   it  had  on  the  average  during\n                        1976.\n                                    The  average  value  of  the   dollar   against\n                        leading  foreign   currencies  has   changed  little\n                        over   the  past  month.     In  January  the  U.   S.\n                        foreign  trade   deficit   increased   further;\n                        exports   were  down  a   little   from  the  fourth\n                        quarter   rate   and  imports  were  substantially\n                        higher.\n                                    Growth  in  M-1   slowed  sharply   in   February\n                        from  the  moderate  pace   in  January.     At  banks\n                        and  thrift  institutions,   inflows   of   time\n                        and  savings  deposits  other   than   large\n                        denomination  CD's  continued  to   slacken.\n                       Business   demands   for  short-term   credit   appear\n                        to  have   strengthened  further   in   early  1977.\n                        Since  mid-Februay  short-term  market  interest\n                        rates   have  changed  little  on   balance,  but  most\n                        longer-term  rates  have  edged  higher.\n                                    In   light  of   the   foregoing  developments,\n                        it   is   the  policy  of   the  Federal  Open  Market\n                        Committee  to   foster  bank  reserve  and   other\n                        financial  conditions   that  will   encourage\n                        continued  economic   expansion,  while  resisting\n                        inflationary  pressures  and  contributing   to  a\n                        sustainable    pattern  of   international   trans\n                        actions.\n                                   At   its  meeting   on  January   18,   1977,  the\n                        Committee  agreed   that   growth  of  M-1,   M-2,  and\n                        M-3  within  ranges  of  4-1/2   to   6-1/2  per  cent,\n                        7   to  10   per  cent,   and  8-1/2  to   11-1/2  per  cent,\n                        respectively,   from  the  fourth  quarter  of   1976\n                        to  the  fourth  quarter  of   1977  appears  to\n                        be  consistent  with  these  objectives.\n3/15/77                                                          -   7  -\n                         These  ranges  are  subject   to  reconsideration\n                         at  any  time  as   conditions  warrant.\n                                    The  Committee  seeks   to  encourage  near\n                         term  rates  of   growth  in  M-1  and  M-2  on  a\n                        path  believed  to  be   reasonably  consistent\n                        with  the   longer-run   ranges   for  monetary\n                         aggregates  cited   in  the  preceding  paragraph.\n                         Specifically,  at  present,   it   expects  the\n                         annual   growth  rates   over  the  March-April\n                        period  to  be  within   the  ranges  of  4-1/2  to\n                         8-1/2  per  cent   for  M-1   and  7  to   11   per  cent\n                         for  M-2.     In  the  judgment   of   the  Committee\n                         such  growth  rates   are   likely  to  be  associ\n                         ated  with  a  weekly  average  Federal  funds   rate\n                        of   about   4-5/8   to  4-3/4  per   cent.                                        If,\n                        giving   approximately  equal  weight   to  M-1\n                         and  M-2,   it   appears  that   growth  rates  over\n                        the   2-month  period  will  deviate   significantly\n                        from  the  mid-points   of  the   indicated  ranges,\n                        the  operational   objective   for  the   Federal\n                         funds  rate  shall  be  modified  in  an  orderly\n                         fashion  within   a  range   of  4-1/4   to  5-1/4\n                        per  cent.\n                                    If   it   appears  during   the  period  before\n                        the  next  meeting  that   the  operating   con\n                        straints   specified  above  are  proving  to  be\n                        significantly  inconsistent,   the   Manager  is\n                        promptly  to  notify  the  Chairman  who  will\n                        then  decide  whether  the   situation   calls   for\n                        supplementary  instructions   from  the  Committee.\n                        Consideration  was  then   given   to  the   continuing\n authorizations   of  the  Committee,   in   accordance  with   the\n customary  practice  of   reviewing   such  matters  at   the   first\nmeeting   in  March  of   every  year.\n                        Secretary's  note:     On  February  25,   1977,\n                        certain  continuing  authorizations  of   the\n                        Committee,   listed  below,  had  been  distributed\n                        by  the  Secretary  with  the  advice  that,   in\n                        accordance  with  procedures   approved  by  the\nions  of   the\n\n                        Committee,   listed  below,  had  been  distributed\n\n                        by  the  Secretary  with  the  advice  that,   in\n\n                        accordance  with  procedures   approved  by  the\n\n\n", "matches": []}