{"doc_id": "1993-03-23-fomc-minutes", "date": "1993-03-23", "chair": "Alan Greenspan", "combined_score": 0.0, "combined_label": "neutral", "lexicon_score": 0.0, "word_count": 5654, "text": "  Minutes of the Federal Open Market Committee \n  A meeting of the Federal Open Market Committee was held in \n    the offices of the Board of Governors of the Federal Reserve System in \n    Washington, D.C.,  on Tuesday, March 23,  1993,  at  9:00 a.m. \n    Messrs. Broaddus, Jordan, Forrestal, and Parry,\n      Alternate Members of the Federal Open Market\n    Messrs. Hoenig, Melzer, and Syron, Presidents\n      of the Federal Reserve Banks of Kansas City,\n      St. Louis, and Boston, respectively\n      Mr. Patrikis, Deputy General Counsel\n    Messrs. R. Davis, Lang, Lindsey, Rolnick,\n      Rosenblum, Scheld, Siegman, Simpson, and\n    Mr. McDonough, Manager of the System Open Market\n    Ms. Greene, Deputy Manager for Foreign\n    Ms. Lovett, Deputy Manager for Domestic\n    Mr. Ettin, Deputy Director, Division of Research\n      and Statistics, Board of Governors\n    Mr. Winn,1 Assistant to the Board, Office of Board\n    Mr. Madigan, Assistant Director, Division of Monetary\n    Mr. Hooper, Assistant Director, Division of International\n    Ms. Low, Open Market Secretariat Assistant,\n      Division of Monetary Affairs, Board of Governors\n    Messrs. Beebe, T. Davis, Dewald, Goodfriend, and\n      Ms. Tschinkel, Senior Vice Presidents, Federal\n      Reserve Banks of San Francisco, Kansas City,\n      St. Louis, Richmond, and Atlanta, respectively\n    Ms. Browne, and Mr. Sniderman, Vice Presidents, Federal\n      Reserve Banks of Boston and Cleveland, respectively\n    Ms. Krieger, Manager, Open Market Operations,\n      Federal Reserve Bank of New York    \n      1. Attended portion of meeting relating to discussion of merging \n        minutes of action and policy record into one document. \n  At the start of the meeting, the subcommittee established to \n    review policies relating to the release of Committee information \n    reported on its further deliberations and proposed a merging of the \n    current &quot;Minutes of Actions&quot; and the &quot;Record of Policy Actions&quot; into a \n    new document to be designated &quot;Minutes of the Federal Open Market \n    Committee Meeting.&quot; Merging the two documents would put in convenient \n    form all the information that is released pertaining to FOMC meetings, \n    and the new document would be made public on the same schedule as its \n    predecessor documents. The Committee members endorsed the subcommittee's proposal and by unanimous vote the Committee approved the \n    &quot;Minutes of the Federal Open Market Committee Meeting&quot; held on \n    February 2-3, 1993; this merged document was scheduled to be released \n  The Manager of the System Open Market Account reported on \n    developments in foreign exchange markets since the previous meeting on \n    February 2-3, 1993. There were no System open market transactions in \n    foreign currencies during this intermeeting period, and thus no vote \n  The Deputy Manager for Domestic Operations reported on \n    developments in domestic financial markets and on System open market \n    transactions in government securities and federal agency obligations \n    during the period February 3, 1993, through March 22, 1993. By \n    unanimous vote, the Committee ratified these transactions.\n  The Committee then turned to a discussion of the economic \n    outlook and the implementation of monetary policy over the inter-meeting period ahead. A summary of the economic and financial \n    information available at the time of the meeting and of the \n    Committee's discussion is provided below, followed by the domestic \n    policy directive that was approved by the Committee and issued to \n    the Federal Reserve Bank of New York.\n  The information reviewed at this meeting suggested that \n    economic activity was expanding at a more moderate pace in the early \n    months of 1993 after increasing substantially in the fourth quarter. \n    Although outlays for business equipment apparently remained on a \n    strong upward trajectory, sales of new homes had slackened and \n    consumer spending was rising less rapidly. Indicators of production \n    activity also were mixed: Industrial output had continued to post \n    solid gains, but homebuilding had been less robust since year-end. \n    Payroll employment had strengthened, and the unemployment rate had \n    moved down further. Increases in wages had remained subdued in recent \n    months, but advances in consumer and producer prices had been larger \n    than those recorded in the latter part of 1992.\n  Total nonfarm payroll employment rose sharply in February, \n    following generally small advances in previous months, and the length \n    of the average workweek remained at the fourth-quarter level. The \n    strong job gains in construction, services, and retail trade in \n    February apparently reflected to some extent a partial reversal of the \n    special factors that had depressed reported employment in these \n    sectors in previous months. Since December, initial claims for \n    unemployment insurance had fluctuated in a range that was consistent \n    with further modest growth in employment. The civilian unemployment \n    rate edged lower again in February, to 7.0 percent.\n  Industrial production continued to rise at a fairly brisk \n    pace in January and February. Changes in mining and utilities were \n    about offsetting on balance over the two months, but increases in \n    manufacturing were fairly widespread. Although motor vehicle assemblies fell in February from a relatively high January level, the \n    production of consumer durables and computers turned up sharply. \n    In addition, increases in output were recorded in several other \n    categories, including non-energy materials and construction supplies. \n    Recent surveys indicated that new orders for durable goods increased \n    further in February, and lean factory inventories coupled with reports \n    of lengthening delivery times suggested further gains in industrial \n    output in coming months. Total utilization of industrial capacity \n  Retail sales advanced in February after a fourth-quarter \n    surge and a pause in January. Sales at automotive dealers weakened in \n    February. However, there were sharp increases in sales of building \n    materials and supplies, miscellaneous durable goods, and nondurable \n    goods other than apparel. After registering sizable gains late last \n    year, housing starts fell substantially in January and retraced only \n    part of that decline in February. The slowdown was concentrated in \n    single-family housing starts; multifamily starts were up in February \n    from a historically low level in January. Although mortgage interest \n    rates had dropped to the lowest levels in decades, sales of both new \n    and existing homes turned down in January from their high December \n  Incoming data on orders and shipments of nondefense capital \n    goods suggested a further brisk advance in outlays for business \n    equipment in coming months. In January, a decline in shipments of \n    nondefense capital goods only partially reversed a large December \n    rise, as a surge in shipments of computing equipment helped sustain \n    the overall level. Shipments of complete civilian aircraft posted a \n    solid gain in January. The increase appeared to be concentrated in \n    sales to foreign purchasers; in the domestic airline industry, intense \n    competition was forcing cutbacks of unprofitable routes and reductions \n    in both the number of planes in service and orders for new planes. \n    Shipments of durable equipment other than computers and aircraft fell \n    in January to about the level of the fourth quarter. On the other \n    hand, the January reading on new orders for these goods was well above \n    the average for the fourth quarter, suggesting that additional \n    advances in shipments might lie ahead. Nonresidential construction \n    activity was down slightly further in January, reflecting persisting \n    declines in office and industrial building in an environment of excess \n    supply and some continuing, though perhaps lessening, downward \n    pressure on the prices of such structures.\n  Business inventories appeared to have edged lower in January. \n    In manufacturing, factory stocks were drawn down further, and most \n    industries had relatively low stocks-to-shipments ratios. Among \n    wholesalers, strong January sales pulled down inventories at many \n    types of establishments; in numerous cases, a large accumulation of \n    stocks in the fourth quarter was reversed. For the wholesale sector \n    as a whole, the inventories-to-sales ratio in January was near the \n    bottom of the range of the past two years. Retail inventories rose \n    somewhat further in January after a large December increase. Stocks \n    at automotive dealers accounted for all of the January accumulation. \n    At retail stores other than auto dealers, the ratio of inventories-to-sales remained within the narrow range observed over the past year.\n  The nominal U.S. merchandise trade deficit widened slightly \n    in January but was little changed from its average level in the fourth \n    quarter. The value of both exports and imports dropped sharply in \n    January from the December levels. The decline in imports was spread \n    widely among major trade categories, but the decrease in exports \n    largely reflected a reduction in shipments of aircraft after a strong \n    December rise. Among the major foreign industrialized countries, the \n    level of real activity contracted further in the fourth quarter in \n    Japan, western Germany, and France; for the first quarter, the limited \n    data available were generally weak for Japan and France but somewhat \n    more mixed for western Germany. By contrast, economic activity \n    appeared to be increasing in Canada and the United Kingdom.\n  Producer prices of finished goods were up in January and \n    February after changing little over the fourth quarter. Producer \n    prices of finished foods declined over the first two months of the \n    year, but prices of finished energy products climbed rapidly, and \n    prices of other finished items rose at a faster rate than in 1992. At \n    the consumer level, price increases in January and February also were \n    on the high side of the past year's advances. Food prices jumped in \n    January and rose slightly further in February, while energy prices \n    retraced most of a sharp January rise. Excluding food and energy \n    items, consumer prices advanced at a substantially faster pace over \n    the January-February period than in 1992. Increases in wages, as \n    measured by average hourly earnings of production or nonsupervisory \n    workers, remained subdued in recent months. The advance in average \n    hourly earnings slowed in February, and the rise over the twelve \n    months ended in February was considerably smaller than over the \n  At its meeting on February 2-3, 1993, the Committee adopted a \n    directive that called for maintaining the existing degree of pressure \n    on reserve positions and that did not include a presumption about the \n    likely direction of any adjustments to policy during the intermeeting \n    period. Accordingly, the directive indicated that in the context of \n    the Committee's long-run objectives for price stability and \n    sustainable economic growth, and giving careful consideration to \n    economic, financial, and monetary developments, slightly greater \n    reserve restraint or slightly lesser reserve restraint would be \n    acceptable during the intermeeting period. The reserve conditions \n    associated with this directive were expected to be consistent with \n    little change in the levels of M2 and M3 over the two-month period \n  Open market operations during the intermeeting period were \n    directed toward maintaining the existing degree of pressure on reserve \n    positions. Adjustment plus seasonal borrowing averaged only slightly \n    above expected levels in the three full reserve maintenance periods in \n    the intermeeting interval. For the period as a whole, the federal \n    funds rate remained close to the 3 percent level that had prevailed in \n  Other short-term interest rates changed little over the \n    intermeeting period, while long-term rates fell appreciably on \n    balance. Bond markets rallied over most of the period, reflecting \n    market assessments of improved prospects for significant reductions in \n    the federal budget deficit in coming years and the consequences for \n    overall spending. Prices of Treasury notes and bonds also were \n    boosted by municipal defeasance activity and by perceptions of \n    heightened prepayment risks in mortgage-backed securities. In early \n    March, interest rates on long-term Treasury bonds and conventional \n    fixed-rate mortgages reached their lowest levels since 1973, but some \n    of the decline in bond and mortgage rates subsequently was reversed in \n    response to increased apprehension about inflation. Equity prices \n    generally responded favorably to the drop in long-term interest rates, \n    but concerns about future changes in government policy toward a number \n    of industries, including health care, led to lower prices in some \n  In foreign exchange markets, the trade-weighted value of the \n    dollar in terms of the other G-10 currencies fell on balance over the \n    intermeeting period. The dollar depreciated through late February, \n    partly in response to declines in U.S. long-term interest rates and \n    incoming data that were seen as pointing to some slowing of the \n    expansion in the United States. Subsequently, the dollar rebounded in \n    the wake of unexpectedly strong U.S. employment statistics, disappointing inflation numbers, and further signs of weakening economic \n    activity abroad. Near the end of the period, the dollar again dropped \n    against the German mark and other European currencies, following a cut \n    by the Bundesbank of its discount rate that apparently was less than \n    market participants were expecting. On balance over the period, the \n    dollar was marginally lower against the mark and other European \n    currencies, but it declined substantially against the Japanese yen, \n  M2 and M3 contracted in January and February. Part of the \n    weakness apparently reflected temporary factors, such as distortions \n    in seasonal adjustment factors and a lull in prepayments of mortgage-backed securities that reduced deposits held in association with this \n    activity. More fundamentally, relatively attractive returns on \n    capital market instruments continued to prompt households to shift \n    large amounts of liquid balances into market investments, such as bond \n    and stock mutual fund shares. In addition, banks continued to issue \n    subordinated debt and equity to improve their balance sheets at a \n    time when the expansion of bank credit was slowing noticeably; in \n    particular, bank lending to businesses had been depressed by paydowns \n    from the proceeds of heavy bond and stock issuance by nonfinancial \n    corporations. Total domestic nonfinancial debt appeared to have \n    expanded somewhat further in January.\n  The staff projection prepared for this meeting suggested that \n    economic activity would grow over the year ahead at a pace that would \n    foster a further gradual reduction in margins of unemployed labor and \n    capital. The projection incorporated the essential elements of the \n    fiscal proposals recently set forth by the Administration; the effects \n    on aggregate demand, all other things equal, were expected to be small \n    over the next several quarters. However, the appreciable declines in \n    long-term interest rates that had occurred in recent months--evidently \n    partly in response to anticipations of intermediate-term deficit \n    reduction--were expected to support substantial additional gains in \n    business and residential investment. Consumer spending would be \n    bolstered by the progress already achieved in reducing debt service \n    burdens and by a gradual lessening of concerns regarding job security, \n    although the higher personal income taxes now envisioned for upper-income taxpayers were expected to be an inhibiting factor. Increases \n    in export demand would be limited in the near term by the continuing \n    weakness in the economies of the major industrialized countries. The \n    persisting slack in resource utilization was expected to be associated \n    with a return to more subdued price increases after a spurt earlier \n  In the Committee's discussion of current and prospective \n    economic conditions, the members remained encouraged by recent \n    developments that they viewed on the whole as tending to confirm their \n    forecasts of sustained economic expansion, though at a pace appreciably below that now indicated for the fourth quarter of 1992. If \n    realized, such economic growth would be associated over time with a \n    further gradual decline in unemployment. While the expansion appeared \n    to have generated some momentum, a number of factors were likely to \n    limit its strength, including ongoing balance sheet and business \n    restructuring activities, the outlook for a more restrictive federal \n    budget, and continuing weakness in key foreign markets. At the same \n    time, greatly reduced interest rates and much improved, if still \n    vulnerable, business and consumer confidence were positive factors in \n    the outlook. Some members cautioned that even though a moderate rate \n    of economic growth could be viewed as the most likely outcome over the \n    forecast horizon, the current expansion differed in important respects \n    from earlier cyclical recoveries and in light of the attendant \n    uncertainties a considerably different result--in either direction--could not be ruled out. With regard to the outlook for inflation, the \n    faster increases in consumer prices in recent months and a sharp \n    upturn in the prices of certain producer materials tended to raise \n    concerns, or at least a degree of unease, with regard to underlying \n    inflation trends. While these developments might well prove to be an \n    aberration rather than a signal of intensifying inflation, they did \n    suggest the need to reassess the likelihood of a further decline in \n    inflation and to be alert to further signs of a sustained upturn. For \n    now, however, the favorable trends in underlying unit labor costs, \n    which were associated in turn with ongoing gains in productivity and \n    the absence of any firming in wage pressures, led many members to \n    conclude that recent price developments did not provide persuasive \n    evidence of a change in the inflation outlook.\n  Members continued to report somewhat uneven business conditions across the nation. Steady economic growth characterized many \n    parts of the country, but business activity remained depressed in some \n    areas and industries, notably those related to defense, aerospace, and \n    nonresidential construction. While business sentiment was generally \n    positive, many business contacts were uncertain about the outlook for \n    demand in their own industries or the potential strength of the \n    overall expansion, and recent fiscal policy developments appeared to \n    have introduced a further note of caution. This uncertainty helped to \n    account for the continuing reliance of numerous firms on overtime work \n    to meet growing demand rather than incurring the considerable costs of \n    adding new workers. Even so, an increasing number of contacts were \n    reporting worker recalls or new hires. One member commented that job \n    growth could be viewed both as a measure of business sentiment and as \n    a necessary element in building or maintaining consumer confidence and \n    thus helping to ensure an enduring economic expansion.\n  The quickening recovery during 1992, especially in the second \n    half of the year, had received considerable impetus from consumer \n    spending, and while growth in such spending could be expected to \n    moderate from its pace in recent quarters, the consumer sector was \n    viewed as likely to play a key role in sustaining the expansion this \n    year. Many consumers had taken advantage of steep declines in \n    interest rates to strengthen their balance sheets and reduce their \n    debt service burdens, and they were now in a much improved position to \n    finance further growth in their expenditures. The members took note \n    of recent indications of a decline in consumer confidence and of some \n    softening in retail sales since early in the year. However, the \n    latter appeared to be in part the result of recently adverse weather \n    conditions in some major parts of the country, and consumer confidence \n    was still much improved on balance since earlier in the recovery. \n    Accordingly, recent developments were not seen in themselves as \n    harbingers of a weakening consumer spending trend over the next \n  Business spending on producers' durable equipment also was \n    believed likely to continue to provide appreciable stimulus to the \n    expansion assuming that the much reduced interest rates and currently \n    favorable business attitudes would be sustained and that proposed \n    investment tax credit legislation eventually would be enacted. At the \n    same time, business spending for nonresidential structures probably \n    would continue to be held back by weakness in office construction \n    stemming from widespread overcapacity. While office building activity \n    was likely to be restrained for an extended period, members saw some \n    positive signs that pointed to a degree of stabilization in this \n    sector, including the leveling out or even a marginal pickup in rents \n    and occupancy rates in some markets that previously had been severely \n    depressed. A slow turnaround in other building activity was reported \n    in some regions, notably for industrial and retail structures.\n  While the available data on starts of single-family houses \n    in January and February were somewhat disappointing, the members felt \n    that housing construction activity had held up relatively well thus \n    far this year, after allowing for the adverse weather conditions that \n    had retarded construction in some areas. The greatly reduced cost of \n    mortgage financing pointed to continuing gains in housing construction \n    despite a rise in costs associated with the sharp jump in lumber \n    prices and a scarcity of finished building lots in some areas.\n  The members agreed that the prospects for overall spending on \n    business capital goods and housing were vulnerable to shifts in \n    attitudes that might be triggered, for example, by increases in market \n    interest rates associated with an absence of progress in reducing the \n    federal budget deficit. The outlook for a significant contraction in \n    the federal deficit was subject to considerable uncertainty, \n    especially in light of the still pending decisions to be made with \n    regard to health care programs and their financing. The members \n    recognized that the direct effects of appreciable deficit reduction \n    would tend to constrain economic activity, as evidenced by the impact \n    in many areas of the defense cutbacks that were already being \n    implemented. Business contacts had expressed concerns about the \n    potential effects on their industries and local markets of various \n    provisions in the proposed legislation. Even so, a more encompassing \n    assessment of the effects of deficit reduction needed to take account \n    of its favorable implications for domestic interest rates. Moreover, \n    insofar as the nearer-term outlook was concerned, the fiscal \n    legislation now under consideration included new spending initiatives \n    and the investment tax credit that were intended to provide some \n    temporary stimulus to an economic expansion that, in the view of many \n    observers, might still be in the process of gathering sustainable \n    momentum. On balance, substantial deficit reduction in line with the \n    currently proposed legislation was seen as likely to have a positive \n    effect on business and consumer confidence, financial markets, and the \n  Several members observed that the outlook for exports had \n    worsened as a result of weakening economic trends in a number of major \n    industrialized nations. Members also commented on the uncertainties \n    in the outlook for foreign trade associated with a variety of \n    political risks abroad and the persisting protectionism that currently \n    was highlighted by strong opposition to key trade agreements now under \n    negotiation or under consideration for ratification. Anecdotal \n    information from business contacts involved in export markets \n    continued to suggest lagging foreign demands for many U.S. goods; \n    however, backlogs for other products, such as labor-saving capital \n  The members devoted considerable attention to the discussion \n    of various factors underlying the outlook for inflation. The consumer \n    and producer price indexes had been less favorable in January and \n    February than in the latter part of 1992. Also, prices of various \n    industrial and construction materials had firmed since the start of \n    the year in apparent response to rising production and, in some \n    industries, to import or environmental restrictions. Anecdotal \n    reports of increasing costs and prices had begun to appear with \n    somewhat greater frequency in some areas, and pressures to widen \n    profit margins reportedly were strong in a number of industries. In \n    their evaluation of recent inflation developments, however, the \n    members generally gave more weight to the behavior of unit labor \n    costs, which indicated that much of the economy's underlying cost \n    structure did not reflect any signs of a pickup in inflationary \n    pressures. Moreover, from a financial perspective, extensions of \n    credit and growth in overall nonfinancial sector debt were not \n    consistent with an economy that was generating significant inflationary pressures, and the recent behavior of long-term debt markets \n    suggested expectations of more subdued inflation. Against this background, the recent upturn in consumer and certain commodity prices \n    might well represent a temporary development such as had occurred \n    previously during the current cyclical upswing. In support of this \n    view, members cited various fundamentals that seemed inconsistent with \n    accelerating inflation, including the considerable slack in the utilization of labor and capital resources, strong competitive conditions \n    in many markets, the absence of significant lengthening in supplier \n    delivery schedules, and an extended period of weak expansion in the \n    broader monetary aggregates that now encompassed some recent deceleration in M1. Nonetheless, the members acknowledged that recent \n    price developments had raised a degree of unease in their minds, and \n    their concerns would rise if the recent pace of price advances were \n    sustained in the months immediately ahead. One member observed that a \n    somewhat faster economic expansion than currently was expected by most \n    members might well serve to intensify inflation pressures. While \n    price developments were notably difficult to predict, most of the \n    members concluded that the evidence at this point did not confirm a \n    resurgence in inflationary pressures, and some commented that further \n    modest disinflation remained a reasonable expectation for the next \n  In the Committee's discussion of policy for the intermeeting \n    period ahead, most of the members endorsed a proposal to maintain an \n    unchanged degree of pressure on reserve positions, while two members \n    supported an immediate move to tighten reserve conditions. In the \n    majority view, the current degree, of reserve pressure continued to \n    represent a policy stance that was appropriately balanced in light of \n    the opposing risks of a faltering economic expansion and a resurgence \n    of inflation. Conditions in credit markets did not provide confirming \n    evidence of the emergence of greater inflationary pressures and the \n    need to restrain the growth in credit. Indeed, the continuation of \n    balance sheet restructuring activities by financial institutions and \n    the associated caution on the part of these institutions with regard \n    to extending loans still appeared to be exerting a significantly \n    inhibiting effect on the overall growth in spending and economic \n    activity. Several members acknowledged that a policy of maintaining \n    unchanged reserve conditions and an associated federal funds rate \n    around current levels, which implied that real short-term rates were \n    near zero or even slightly negative, could have inflationary \n    consequences in the event of a strengthening of the expansion and a \n    sustained pickup in credit demands. The Committee would need to \n    remain alert to such a development. In present circumstances, \n    however, an unchanged policy stance seemed most consistent with \n    achieving sustained economic expansion in an environment of subdued \n    inflation. The members who favored a prompt move toward restraint \n    were persuaded that a steady policy incurred an unacceptable risk of \n    halting the progress toward price stability and indeed of intensifying \n    inflation as the current expansion matured. In this view, a policy \n    tightening move at this point was likely to counter the need for more \n    substantial and potentially disruptive tightening actions later.\n  In the course of the Committee discussion, the members took \n    account of a staff analysis that pointed to a resumption of M2 and M3 \n    growth over the months ahead. This analysis suggested that the temporary factors depressing the broader monetary aggregates likely would \n    be reversing, but that the other influences causing a rechanneling of \n    credit flows away from depository institutions and boosting the \n    velocity of money undoubtedly would persist, though probably with \n    diminishing force. Accordingly, the staff foresaw moderate growth of \n    M2 and M3 that at midyear would leave these aggregates below the lower \n    ends of the Committee's ranges for 1993. Under prevailing circumstances, such continuing weakness in the broader aggregates was not \n    viewed as indicating inadequate monetary stimulus. Indeed, a number \n    of members commented that other indicators suggested that current \n    monetary policy was in fact quite accommodative as evidenced for \n    example by low short-term interest rates, especially on an inflation-adjusted basis. Moreover, Ml, reserves, and the monetary base had \n    continued to expand in the first quarter, though at much reduced \n    rates. One member commented that the slowdown in these narrower \n    monetary measures, which he viewed as important indicators of the \n    thrust of monetary policy, had favorable implications with regard to \n    bringing inflation under control. The members agreed that the \n    considerable uncertainty that continued to surround the outlook for \n    broad money relative to spending implied that forming precise expectations for monetary growth over the months ahead was not feasible.\n  In the Committee's discussion of possible intermeeting \n    adjustments to the degree of reserve pressure, members who favored an \n    unchanged policy stance also expressed a preference for retaining the \n    symmetry of the existing directive. Some observed that a policy \n    change during the intermeeting period, if any, might well be in the \n    direction of a tightening move. However, because there was no \n    compelling case in the view of most members for such a move at this \n    time and any intermeeting adjustment would be made in the light of \n    emerging developments, a symmetric directive was warranted. In this \n    connection, one member commented that, given the Committee's assessment of current economic and financial conditions, a tilt in the \n    directive toward restraint would give a misleading indication of the \n    Committee's current intentions. Members also noted that a change in \n    policy, should one be called for by intermeeting developments, would \n    represent a shift in the direction of policy and would be likely to \n    have an especially pronounced impact on financial markets.\n  At the conclusion of the Committee's discussion, a majority \n    of the members indicated that they favored a directive that called for \n    maintaining the existing degree of pressure on reserve positions. \n    These members also expressed a preference for a directive that did not \n    include a presumption about the likely direction of any adjustment to \n    policy during the intermeeting period. Accordingly, in the context of \n    the Committee's long-run objectives for price stability and sustainable economic growth, and giving careful consideration to economic, \n    financial, and monetary developments, the Committee decided that \n    slightly greater or slightly lesser reserve restraint would be \n    acceptable during the intermeeting period. The reserve conditions \n    contemplated at this meeting were expected to be consistent with a \n    resumption of moderate growth in M2 and M3 over the second quarter.\n  At the conclusion of the meeting, the Federal Reserve Bank of \n    New York was authorized and directed, until instructed otherwise by \n    the Committee, to execute transactions in the System account in \n    accordance with the following domestic policy directive:\n    The information reviewed at this meeting suggests \n      that economic activity has increased at a more moderate \n      pace in the early months of 1993 after expanding \n      robustly in the fourth quarter. Total nonfarm payroll \n      employment registered a sharp increase in February \n      following generally small advances in previous months, \n      and the civilian unemployment rate edged down further \n      to 7.0 percent. Industrial production continued to \n      post solid gains in January and February. Retail sales \n      increased somewhat further over the first two months of \n      the year after a fourth-quarter surge. Housing starts \n      slipped in early 1993 after registering sizable gains \n      late last year. Incoming data on orders and shipments \n      of nondefense capital goods suggest a further brisk \n      advance in outlays for business equipment, while nonresidential construction has remained soft. The \n      nominal U.S. merchandise trade deficit was essentially \n      unchanged in January from its average level in the \n      fourth quarter, but both exports and imports were substantially lower. Increases in wages have remained \n      subdued, but recent advances in consumer and producer \n      prices have been larger than those recorded in the \n    Short-term interest rates have changed little \n      since the Committee meeting in early February while \n      bond yields have fallen appreciably on balance. In \n      foreign exchange markets, the trade-weighted value of \n      the dollar in terms of the other G-10 currencies \n      declined on balance over the intermeeting period.\n    M2 and M3 contracted in January and February, \n      apparently reflecting transitory factors and further \n      shifts into market investments. Total domestic nonfinancial debt appears to have expanded somewhat \n    The Federal Open Market Committee seeks monetary \n      and financial conditions that will foster price stability and promote sustainable growth in output. In \n      furtherance of these objectives, the Committee at its \n      meeting in February established ranges for growth of M2 \n      and M3 of 2 to 6 percent and 1/2 to 4-1/2 percent \n      respectively, measured from the fourth quarter of 1992 \n      to the fourth quarter of 1993. The Committee expects \n      that developments contributing to unusual velocity \n      increases are likely to persist during the year. The \n      monitoring range for growth of total domestic nonfinancial debt was set at 4-1/2 to 8-1/2 percent for \n      the year. The behavior of the monetary aggregates will \n      continue to be evaluated in the light of progress \n      toward price level stability, movements in their \n      velocities, and developments in the economy and \n    In the implementation of policy for the immediate \n      future, the Committee seeks to maintain the existing \n      degree of pressure on reserve positions. In the \n      context of the Committee's long-run objectives for \n      price stability and sustainable economic growth, and \n      giving careful consideration to economic, financial, \n      and monetary developments, slightly greater reserve \n      restraint or slightly lesser reserve restraint would be \n      acceptable in the intermeeting period. The contemplated reserve conditions are expected to be consistent \n      with a resumption of moderate growth in the broader \n      monetary aggregates over the second quarter.\n    Votes for this action: Messrs. Greenspan, \n      Corrigan, Boehne, Keehn, Kelley, LaWare, McTeer, \n      Mullins, Ms. Phillips, and Mr. Stern.\n    Votes against this action: Messrs. Angell \n  Messrs. Angell and Lindsey indicated that their concerns about \n    the outlook for inflation prompted them to favor an immediate move to \n    tighten reserve conditions. In their view, such an action was desirable \n    not only to arrest the possible emergence of greater inflation but \n    especially to promote further disinflation. They were persuaded that \n    monetary policy currently was overly accommodative as suggested by \n    various indicators such as recent data on consumer and producer prices, \n    the upswing in commodity prices, the low level of real short-term \n    interest rates, and what in their judgment was a relatively depressed \n    foreign exchange value of the dollar given the comparative strength of \n    the U.S. economy and international interest rate trends. They noted \n    that the current federal funds rate was probably not sustainable in the \n    long term and that a tightening move at this time might well avoid the \n    need for more sizable and potentially disruptive policy actions later.\n  Mr. Angell also emphasized the risks associated with any policy \n    that did not firmly maintain a disinflationary trend. As he interpreted \n    historical precedents, the typical result of a policy that tolerated \n    some inflation was an eventual rise in inflation leading to permanently \n    higher interest rates with adverse effects on economic activity. \n    Indeed, he supported unpegging the federal funds rate to counter \n    incipient price pressures showing through in commodity and finished \n    goods prices. He believed that a clear signal of the Committee's \n    commitment to price level stability would stabilize the price of gold \n    along with the exchange value of the dollar and thereby provide a \n    climate for further reductions in long-and intermediate-term interest \n    rates. Such an approach to policy not only would assure a continuing \n    disinflationary trend and eventual price stability, with very favorable \n    implications for financial markets and economic growth, but it would in \n    his view preclude an unsettling tendency for the debt markets to weaken \n    every time newly available data appeared to suggest that economic growth \n    was strengthening and that further monetary policy tightening actions \n    therefore might be in the offing. In sum, such a policy would provide \n    for the achievement of the Committee's objective of sustaining progress \n    toward price stability which he believed was necessary for maintaining \n    recent higher labor productivity, a permanently higher savings rate, and \n    a prolonged period of economic expansion.\n  It was agreed that the next meeting of the Committee would \n\n\n", "matches": []}